README.md
setup.py
image_create/__init__.py
image_create/create_image.py
image_create.egg-info/PKG-INFO
image_create.egg-info/SOURCES.txt
image_create.egg-info/dependency_links.txt
image_create.egg-info/top_level.txt