Metadata-Version: 2.1
Name: image-create
Version: 0.0.1
Summary: pacote para criação de imagens
Home-page: https://github.com/wagnergama/package_image_create
Author: wagner_gama
Author-email: wagner@dealinformatica.info
Requires-Python: >=3.10
